flask_scrapinghub/FlaskScrapinghub.py
flask_scrapinghub/__init__.py
flask_scrapinghub/flag.py
flask_scrapinghub/spider_base.py
flask_scrapinghub/spider_console.py
flask_scrapinghub/chainspider/__init__.py
flask_scrapinghub/chainspider/spider_base.py
flask_scrapinghub/chainspider/spider_chain.py
flask_scrapinghub/chainspider/spider_node.py
flask_scrapinghub/unispiders/__init__.py
flask_scrapinghub/unispiders/unispider.py
flask_scrapinghub/unispiders/unispider_queue.py
flask_scrapinghub/utils/__init__.py
flask_scrapinghub/utils/color.py
flask_scrapinghub/utils/execution.py
flask_scrapinghub/utils/tag.py
flask_scrapinghub-0.0.8.dist-info/LICENSE
flask_scrapinghub-0.0.8.dist-info/METADATA
flask_scrapinghub-0.0.8.dist-info/WHEEL
flask_scrapinghub-0.0.8.dist-info/top_level.txt
flask_scrapinghub-0.0.8.dist-info/RECORD
